langchain_praisonai/__init__.py
langchain_praisonai/tools.py
langchain_praisonai-0.1.0.dist-info/licenses/LICENSE
langchain_praisonai-0.1.0.dist-info/METADATA
langchain_praisonai-0.1.0.dist-info/WHEEL
langchain_praisonai-0.1.0.dist-info/top_level.txt
langchain_praisonai-0.1.0.dist-info/RECORD
