Metadata-Version: 2.4
Name: langchain-praisonai
Version: 0.1.0
Summary: LangChain integration for PraisonAI multi-agent framework
Author-email: Mervin Praison <support@praison.ai>
License: MIT
Project-URL: Homepage, https://github.com/MervinPraison/praisonai-integrations
Project-URL: Documentation, https://docs.praison.ai
Project-URL: Repository, https://github.com/MervinPraison/praisonai-integrations
Keywords: langchain,praisonai,ai-agents,multi-agent,llm
Classifier: Development Status :: 4 - Beta
Classifier: Intended Audience :: Developers
Classifier: License :: OSI Approved :: MIT License
Classifier: Programming Language :: Python :: 3
Classifier: Programming Language :: Python :: 3.9
Classifier: Programming Language :: Python :: 3.10
Classifier: Programming Language :: Python :: 3.11
Classifier: Programming Language :: Python :: 3.12
Requires-Python: >=3.9
License-File: LICENSE
Requires-Dist: langchain-core>=0.1.0
Requires-Dist: httpx>=0.24.0
Requires-Dist: pydantic>=2.0.0
Provides-Extra: dev
Requires-Dist: pytest>=7.0.0; extra == "dev"
Requires-Dist: pytest-asyncio>=0.21.0; extra == "dev"
Requires-Dist: pytest-httpx>=0.21.0; extra == "dev"
Requires-Dist: black>=23.0.0; extra == "dev"
Requires-Dist: ruff>=0.1.0; extra == "dev"
Dynamic: license-file
